num2azerbaijani/__init__.py
num2azerbaijani/nums.py
num2azerbaijani-0.0.3.dist-info/LICENSE.txt
num2azerbaijani-0.0.3.dist-info/METADATA
num2azerbaijani-0.0.3.dist-info/WHEEL
num2azerbaijani-0.0.3.dist-info/top_level.txt
num2azerbaijani-0.0.3.dist-info/RECORD
