Metadata-Version: 2.1
Name: num2azerbaijani
Version: 0.0.3
Summary: Convert integers into Azerbaijani string
Home-page: https://github.com/YunisDEV/num2azerbaijani
Author: Yunis Huseynzade
Author-email: yunisdev.04@gmail.com
License: UNKNOWN
Platform: UNKNOWN
Classifier: Programming Language :: Python :: 3
Classifier: License :: OSI Approved :: MIT License
Classifier: Operating System :: OS Independent
Requires-Python: >=3.6
